gofish_python/__init__.py
gofish_python/events.py
gofish_python/js_bridge.py
gofish_python/marks.py
gofish_python/node.py
gofish_python/operators.py
gofish_python/render.py
gofish_python/utils.py
gofish_python/wrapper.py
gofish_graphics-0.1.0.dist-info/METADATA
gofish_graphics-0.1.0.dist-info/WHEEL
gofish_graphics-0.1.0.dist-info/top_level.txt
gofish_graphics-0.1.0.dist-info/RECORD
