Metadata-Version: 2.4
Name: gofish-graphics
Version: 0.1.0
Summary: Python wrapper for GoFish Graphics - JavaScript is the source of truth for rendering
Author: GoFish Team
License: MIT
Keywords: visualization,charts,graphics,gofish
Classifier: Development Status :: 3 - Alpha
Classifier: Intended Audience :: Developers
Classifier: License :: OSI Approved :: MIT License
Classifier: Programming Language :: Python :: 3
Classifier: Programming Language :: Python :: 3.8
Classifier: Programming Language :: Python :: 3.9
Classifier: Programming Language :: Python :: 3.10
Classifier: Programming Language :: Python :: 3.11
Classifier: Programming Language :: Python :: 3.12
Classifier: Topic :: Scientific/Engineering :: Visualization
Requires-Python: >=3.8
Provides-Extra: pythonmonkey
Requires-Dist: pythonmonkey; extra == "pythonmonkey"
Provides-Extra: jspybridge
Requires-Dist: jsbridge; extra == "jspybridge"
Provides-Extra: dev
Requires-Dist: pytest>=7.0; extra == "dev"
Requires-Dist: pytest-cov>=4.0; extra == "dev"
Requires-Dist: black>=23.0; extra == "dev"
Requires-Dist: mypy>=1.0; extra == "dev"
Provides-Extra: jupyter
Requires-Dist: ipython>=8.0; extra == "jupyter"
Requires-Dist: jupyter>=1.0; extra == "jupyter"
Provides-Extra: data
Requires-Dist: numpy>=1.20; extra == "data"
Requires-Dist: pandas>=1.3; extra == "data"
Dynamic: requires-python
